{
  "openapi": "3.0.0",
  "info": {
    "title": "Mock Retail API - Customers",
    "version": "1.0.0",
    "description": "Products, orders, customers API - generated from Fastify route schemas."
  },
  "servers": [
    {
      "url": "/",
      "description": "Relative to host"
    }
  ],
  "paths": {
    "/api/customers": {
      "get": {
        "tags": [
          "customers"
        ],
        "responses": {
          "200": {
            "description": "Default Response",
            "content": {
              "application/json": {
                "schema": {
                  "type": "array",
                  "items": {
                    "type": "object",
                    "properties": {
                      "id": {
                        "type": "integer"
                      },
                      "name": {
                        "type": "string"
                      },
                      "email": {
                        "type": "string"
                      },
                      "country": {
                        "type": "string"
                      },
                      "tier": {
                        "type": "string"
                      },
                      "createdAt": {
                        "type": "string"
                      }
                    }
                  }
                }
              }
            }
          }
        }
      },
      "post": {
        "tags": [
          "customers"
        ],
        "requestBody": {
          "required": true,
          "content": {
            "application/json": {
              "schema": {
                "type": "object",
                "required": [
                  "name",
                  "email",
                  "country",
                  "tier"
                ],
                "properties": {
                  "name": {
                    "type": "string"
                  },
                  "email": {
                    "type": "string"
                  },
                  "country": {
                    "type": "string"
                  },
                  "tier": {
                    "type": "string"
                  }
                }
              }
            }
          }
        },
        "responses": {
          "201": {
            "description": "Default Response",
            "content": {
              "application/json": {
                "schema": {
                  "type": "object",
                  "properties": {
                    "id": {
                      "type": "integer"
                    },
                    "name": {
                      "type": "string"
                    },
                    "email": {
                      "type": "string"
                    },
                    "country": {
                      "type": "string"
                    },
                    "tier": {
                      "type": "string"
                    },
                    "createdAt": {
                      "type": "string"
                    }
                  }
                }
              }
            }
          },
          "400": {
            "description": "Default Response",
            "content": {
              "application/json": {
                "schema": {
                  "type": "object",
                  "properties": {
                    "error": {
                      "type": "string"
                    }
                  }
                }
              }
            }
          }
        }
      }
    },
    "/api/customers/stats": {
      "get": {
        "tags": [
          "customers"
        ],
        "responses": {
          "200": {
            "description": "Default Response",
            "content": {
              "application/json": {
                "schema": {
                  "type": "object",
                  "properties": {
                    "total": {
                      "type": "integer"
                    },
                    "byTier": {
                      "type": "object",
                      "additionalProperties": {
                        "type": "integer"
                      }
                    }
                  }
                }
              }
            }
          }
        }
      }
    },
    "/api/customers/tier/{tier}": {
      "get": {
        "tags": [
          "customers"
        ],
        "parameters": [
          {
            "schema": {
              "type": "string"
            },
            "in": "path",
            "name": "tier",
            "required": true
          }
        ],
        "responses": {
          "200": {
            "description": "Default Response",
            "content": {
              "application/json": {
                "schema": {
                  "type": "array",
                  "items": {
                    "type": "object",
                    "properties": {
                      "id": {
                        "type": "integer"
                      },
                      "name": {
                        "type": "string"
                      },
                      "email": {
                        "type": "string"
                      },
                      "country": {
                        "type": "string"
                      },
                      "tier": {
                        "type": "string"
                      },
                      "createdAt": {
                        "type": "string"
                      }
                    }
                  }
                }
              }
            }
          }
        }
      }
    },
    "/api/customers/{id}": {
      "get": {
        "tags": [
          "customers"
        ],
        "parameters": [
          {
            "schema": {
              "type": "string"
            },
            "in": "path",
            "name": "id",
            "required": true
          }
        ],
        "responses": {
          "200": {
            "description": "Default Response",
            "content": {
              "application/json": {
                "schema": {
                  "type": "object",
                  "properties": {
                    "id": {
                      "type": "integer"
                    },
                    "name": {
                      "type": "string"
                    },
                    "email": {
                      "type": "string"
                    },
                    "country": {
                      "type": "string"
                    },
                    "tier": {
                      "type": "string"
                    },
                    "createdAt": {
                      "type": "string"
                    }
                  }
                }
              }
            }
          },
          "400": {
            "description": "Default Response",
            "content": {
              "application/json": {
                "schema": {
                  "type": "object",
                  "properties": {
                    "error": {
                      "type": "string"
                    }
                  }
                }
              }
            }
          },
          "404": {
            "description": "Default Response",
            "content": {
              "application/json": {
                "schema": {
                  "type": "object",
                  "properties": {
                    "error": {
                      "type": "string"
                    }
                  }
                }
              }
            }
          }
        }
      },
      "patch": {
        "tags": [
          "customers"
        ],
        "requestBody": {
          "required": true,
          "content": {
            "application/json": {
              "schema": {
                "type": "object",
                "properties": {
                  "name": {
                    "type": "string"
                  },
                  "email": {
                    "type": "string"
                  },
                  "country": {
                    "type": "string"
                  },
                  "tier": {
                    "type": "string"
                  }
                }
              }
            }
          }
        },
        "parameters": [
          {
            "schema": {
              "type": "string"
            },
            "in": "path",
            "name": "id",
            "required": true
          }
        ],
        "responses": {
          "200": {
            "description": "Default Response",
            "content": {
              "application/json": {
                "schema": {
                  "type": "object",
                  "properties": {
                    "id": {
                      "type": "integer"
                    },
                    "name": {
                      "type": "string"
                    },
                    "email": {
                      "type": "string"
                    },
                    "country": {
                      "type": "string"
                    },
                    "tier": {
                      "type": "string"
                    },
                    "createdAt": {
                      "type": "string"
                    }
                  }
                }
              }
            }
          },
          "400": {
            "description": "Default Response",
            "content": {
              "application/json": {
                "schema": {
                  "type": "object",
                  "properties": {
                    "error": {
                      "type": "string"
                    }
                  }
                }
              }
            }
          },
          "404": {
            "description": "Default Response",
            "content": {
              "application/json": {
                "schema": {
                  "type": "object",
                  "properties": {
                    "error": {
                      "type": "string"
                    }
                  }
                }
              }
            }
          }
        }
      },
      "delete": {
        "tags": [
          "customers"
        ],
        "parameters": [
          {
            "schema": {
              "type": "string"
            },
            "in": "path",
            "name": "id",
            "required": true
          }
        ],
        "responses": {
          "204": {
            "description": "No content"
          },
          "400": {
            "description": "Default Response",
            "content": {
              "application/json": {
                "schema": {
                  "type": "object",
                  "properties": {
                    "error": {
                      "type": "string"
                    }
                  }
                }
              }
            }
          },
          "404": {
            "description": "Default Response",
            "content": {
              "application/json": {
                "schema": {
                  "type": "object",
                  "properties": {
                    "error": {
                      "type": "string"
                    }
                  }
                }
              }
            }
          }
        }
      }
    }
  },
  "components": {
    "schemas": {
      "Error": {
        "type": "object",
        "properties": {
          "error": {
            "type": "string"
          }
        }
      },
      "Product": {
        "type": "object",
        "properties": {
          "id": {
            "type": "string"
          },
          "name": {
            "type": "string"
          },
          "category": {
            "type": "string"
          },
          "price": {
            "type": "number"
          },
          "stock": {
            "type": "integer"
          },
          "sku": {
            "type": "string"
          },
          "active": {
            "type": "boolean"
          }
        }
      },
      "Order": {
        "type": "object",
        "properties": {
          "id": {
            "type": "string"
          },
          "customerId": {
            "type": "integer"
          },
          "status": {
            "type": "string"
          },
          "createdAt": {
            "type": "string"
          },
          "items": {
            "type": "array",
            "items": {
              "type": "object",
              "properties": {
                "productId": {
                  "type": "string"
                },
                "qty": {
                  "type": "integer"
                }
              }
            }
          },
          "customer": {
            "type": "string"
          },
          "country": {
            "type": "string"
          },
          "total": {
            "type": "string"
          }
        }
      },
      "Customer": {
        "type": "object",
        "properties": {
          "id": {
            "type": "integer"
          },
          "name": {
            "type": "string"
          },
          "email": {
            "type": "string"
          },
          "country": {
            "type": "string"
          },
          "tier": {
            "type": "string"
          },
          "createdAt": {
            "type": "string"
          }
        }
      },
      "OrderItem": {
        "type": "object",
        "properties": {
          "productId": {
            "type": "string"
          },
          "qty": {
            "type": "integer"
          }
        }
      }
    }
  }
}