{
  "openapi": "3.0.0",
  "info": {
    "title": "Mock Retail API - Orders",
    "version": "1.0.0",
    "description": "Products, orders, customers API - generated from Fastify route schemas."
  },
  "servers": [
    {
      "url": "/",
      "description": "Relative to host"
    }
  ],
  "paths": {
    "/api/orders": {
      "get": {
        "tags": [
          "orders"
        ],
        "responses": {
          "200": {
            "description": "Default Response",
            "content": {
              "application/json": {
                "schema": {
                  "type": "array",
                  "items": {
                    "type": "object",
                    "properties": {
                      "id": {
                        "type": "string"
                      },
                      "customerId": {
                        "type": "integer"
                      },
                      "status": {
                        "type": "string"
                      },
                      "createdAt": {
                        "type": "string"
                      },
                      "items": {
                        "type": "array",
                        "items": {
                          "type": "object",
                          "properties": {
                            "productId": {
                              "type": "string"
                            },
                            "qty": {
                              "type": "integer"
                            }
                          }
                        }
                      },
                      "customer": {
                        "type": "string"
                      },
                      "country": {
                        "type": "string"
                      },
                      "total": {
                        "type": "string"
                      }
                    }
                  }
                }
              }
            }
          }
        }
      },
      "post": {
        "tags": [
          "orders"
        ],
        "requestBody": {
          "required": true,
          "content": {
            "application/json": {
              "schema": {
                "type": "object",
                "required": [
                  "customerId",
                  "items"
                ],
                "properties": {
                  "customerId": {
                    "type": "integer"
                  },
                  "items": {
                    "type": "array",
                    "items": {
                      "type": "object",
                      "properties": {
                        "productId": {
                          "type": "string"
                        },
                        "qty": {
                          "type": "integer"
                        }
                      }
                    }
                  }
                }
              }
            }
          }
        },
        "responses": {
          "201": {
            "description": "Default Response",
            "content": {
              "application/json": {
                "schema": {
                  "type": "object",
                  "properties": {
                    "id": {
                      "type": "string"
                    },
                    "customerId": {
                      "type": "integer"
                    },
                    "status": {
                      "type": "string"
                    },
                    "createdAt": {
                      "type": "string"
                    },
                    "items": {
                      "type": "array",
                      "items": {
                        "type": "object",
                        "properties": {
                          "productId": {
                            "type": "string"
                          },
                          "qty": {
                            "type": "integer"
                          }
                        }
                      }
                    },
                    "customer": {
                      "type": "string"
                    },
                    "country": {
                      "type": "string"
                    },
                    "total": {
                      "type": "string"
                    }
                  }
                }
              }
            }
          },
          "400": {
            "description": "Default Response",
            "content": {
              "application/json": {
                "schema": {
                  "type": "object",
                  "properties": {
                    "error": {
                      "type": "string"
                    }
                  }
                }
              }
            }
          },
          "404": {
            "description": "Default Response",
            "content": {
              "application/json": {
                "schema": {
                  "type": "object",
                  "properties": {
                    "error": {
                      "type": "string"
                    }
                  }
                }
              }
            }
          }
        }
      }
    },
    "/api/orders/revenue": {
      "get": {
        "tags": [
          "orders"
        ],
        "responses": {
          "200": {
            "description": "Default Response",
            "content": {
              "application/json": {
                "schema": {
                  "type": "object",
                  "properties": {
                    "total": {
                      "type": "number"
                    },
                    "byStatus": {
                      "type": "object",
                      "additionalProperties": {
                        "type": "integer"
                      }
                    }
                  }
                }
              }
            }
          }
        }
      }
    },
    "/api/orders/customer/{customerId}": {
      "get": {
        "tags": [
          "orders"
        ],
        "parameters": [
          {
            "schema": {
              "type": "string"
            },
            "in": "path",
            "name": "customerId",
            "required": true
          }
        ],
        "responses": {
          "200": {
            "description": "Default Response",
            "content": {
              "application/json": {
                "schema": {
                  "type": "array",
                  "items": {
                    "type": "object",
                    "properties": {
                      "id": {
                        "type": "string"
                      },
                      "customerId": {
                        "type": "integer"
                      },
                      "status": {
                        "type": "string"
                      },
                      "createdAt": {
                        "type": "string"
                      },
                      "items": {
                        "type": "array",
                        "items": {
                          "type": "object",
                          "properties": {
                            "productId": {
                              "type": "string"
                            },
                            "qty": {
                              "type": "integer"
                            }
                          }
                        }
                      },
                      "customer": {
                        "type": "string"
                      },
                      "country": {
                        "type": "string"
                      },
                      "total": {
                        "type": "string"
                      }
                    }
                  }
                }
              }
            }
          },
          "400": {
            "description": "Default Response",
            "content": {
              "application/json": {
                "schema": {
                  "type": "object",
                  "properties": {
                    "error": {
                      "type": "string"
                    }
                  }
                }
              }
            }
          }
        }
      }
    },
    "/api/orders/{id}": {
      "get": {
        "tags": [
          "orders"
        ],
        "parameters": [
          {
            "schema": {
              "type": "string"
            },
            "in": "path",
            "name": "id",
            "required": true
          }
        ],
        "responses": {
          "200": {
            "description": "Default Response",
            "content": {
              "application/json": {
                "schema": {
                  "type": "object",
                  "properties": {
                    "id": {
                      "type": "string"
                    },
                    "customerId": {
                      "type": "integer"
                    },
                    "status": {
                      "type": "string"
                    },
                    "createdAt": {
                      "type": "string"
                    },
                    "items": {
                      "type": "array",
                      "items": {
                        "type": "object",
                        "properties": {
                          "productId": {
                            "type": "string"
                          },
                          "qty": {
                            "type": "integer"
                          }
                        }
                      }
                    },
                    "customer": {
                      "type": "string"
                    },
                    "country": {
                      "type": "string"
                    },
                    "total": {
                      "type": "string"
                    }
                  }
                }
              }
            }
          },
          "404": {
            "description": "Default Response",
            "content": {
              "application/json": {
                "schema": {
                  "type": "object",
                  "properties": {
                    "error": {
                      "type": "string"
                    }
                  }
                }
              }
            }
          }
        }
      }
    },
    "/api/orders/{id}/advance": {
      "patch": {
        "tags": [
          "orders"
        ],
        "parameters": [
          {
            "schema": {
              "type": "string"
            },
            "in": "path",
            "name": "id",
            "required": true
          }
        ],
        "responses": {
          "200": {
            "description": "Default Response",
            "content": {
              "application/json": {
                "schema": {
                  "type": "object",
                  "properties": {
                    "id": {
                      "type": "string"
                    },
                    "customerId": {
                      "type": "integer"
                    },
                    "status": {
                      "type": "string"
                    },
                    "createdAt": {
                      "type": "string"
                    },
                    "items": {
                      "type": "array",
                      "items": {
                        "type": "object",
                        "properties": {
                          "productId": {
                            "type": "string"
                          },
                          "qty": {
                            "type": "integer"
                          }
                        }
                      }
                    },
                    "customer": {
                      "type": "string"
                    },
                    "country": {
                      "type": "string"
                    },
                    "total": {
                      "type": "string"
                    }
                  }
                }
              }
            }
          },
          "404": {
            "description": "Default Response",
            "content": {
              "application/json": {
                "schema": {
                  "type": "object",
                  "properties": {
                    "error": {
                      "type": "string"
                    }
                  }
                }
              }
            }
          }
        }
      }
    },
    "/api/orders/{id}/cancel": {
      "post": {
        "tags": [
          "orders"
        ],
        "parameters": [
          {
            "schema": {
              "type": "string"
            },
            "in": "path",
            "name": "id",
            "required": true
          }
        ],
        "responses": {
          "200": {
            "description": "Default Response",
            "content": {
              "application/json": {
                "schema": {
                  "type": "object",
                  "properties": {
                    "cancelled": {
                      "type": "boolean"
                    }
                  }
                }
              }
            }
          },
          "400": {
            "description": "Default Response",
            "content": {
              "application/json": {
                "schema": {
                  "type": "object",
                  "properties": {
                    "error": {
                      "type": "string"
                    }
                  }
                }
              }
            }
          }
        }
      }
    }
  },
  "components": {
    "schemas": {
      "Error": {
        "type": "object",
        "properties": {
          "error": {
            "type": "string"
          }
        }
      },
      "Product": {
        "type": "object",
        "properties": {
          "id": {
            "type": "string"
          },
          "name": {
            "type": "string"
          },
          "category": {
            "type": "string"
          },
          "price": {
            "type": "number"
          },
          "stock": {
            "type": "integer"
          },
          "sku": {
            "type": "string"
          },
          "active": {
            "type": "boolean"
          }
        }
      },
      "Order": {
        "type": "object",
        "properties": {
          "id": {
            "type": "string"
          },
          "customerId": {
            "type": "integer"
          },
          "status": {
            "type": "string"
          },
          "createdAt": {
            "type": "string"
          },
          "items": {
            "type": "array",
            "items": {
              "type": "object",
              "properties": {
                "productId": {
                  "type": "string"
                },
                "qty": {
                  "type": "integer"
                }
              }
            }
          },
          "customer": {
            "type": "string"
          },
          "country": {
            "type": "string"
          },
          "total": {
            "type": "string"
          }
        }
      },
      "Customer": {
        "type": "object",
        "properties": {
          "id": {
            "type": "integer"
          },
          "name": {
            "type": "string"
          },
          "email": {
            "type": "string"
          },
          "country": {
            "type": "string"
          },
          "tier": {
            "type": "string"
          },
          "createdAt": {
            "type": "string"
          }
        }
      },
      "OrderItem": {
        "type": "object",
        "properties": {
          "productId": {
            "type": "string"
          },
          "qty": {
            "type": "integer"
          }
        }
      }
    }
  }
}